koenigsberg-0.1.10.dist-info/METADATA
koenigsberg-0.1.10.dist-info/WHEEL
koenigsberg-0.1.10.dist-info/license_files/LICENSE
koenigsberg/main.py
koenigsberg/tests/test_register.py
koenigsberg/tests/conftest.py
koenigsberg/tests/__init__.py
koenigsberg/examples/__init__.py
koenigsberg/__init__.py
koenigsberg/_internal.abi3.so
koenigsberg-0.1.10.dist-info/RECORD
