Metadata-Version: 2.3
Name: koenigsberg
Version: 0.1.10
Classifier: Programming Language :: Rust
Classifier: Programming Language :: Python :: Implementation :: CPython
Classifier: Programming Language :: Python :: Implementation :: PyPy
Requires-Dist: ibis-framework ==9.0.0 ; python_version >= '3.10' and python_version < '4.0'
Requires-Dist: dask ==2023.12.1 ; python_version >= '3.10' and python_version < '4.0'
Requires-Dist: attrs ==23.2.0 ; python_version >= '3.10' and python_version < '4.0'
Requires-Dist: connectorx ==0.3.2 ; python_version >= '3.10' and python_version < '4.0'
Requires-Dist: psycopg2-binary ==2.9.9 ; python_version >= '3.10' and python_version < '4.0'
Requires-Dist: sqlalchemy ==2.0.29 ; python_version >= '3.10' and python_version < '4.0'
Requires-Dist: pyarrow ==13.0.0 ; python_version >= '3.10' and python_version < '4.0'
Requires-Dist: palmerpenguins ==0.1.4 ; python_version >= '3.10' and python_version < '4.0'
Requires-Dist: structlog ==24.2.0 ; python_version >= '3.10' and python_version < '4.0'
Requires-Dist: pytest ==7.4.2 ; python_version >= '3.10' and python_version < '4.0'
Requires-Dist: pytest-mock ==3.14.0 ; python_version >= '3.10' and python_version < '4.0'
License-File: LICENSE
Summary: A really cool placeholder project for testing ideas
Author-email: Daniel Mesejo <mesejoleon@gmail.com>
Requires-Python: >=3.7
